{
  "batch_id": "tier0-computation_batch_0040",
  "source_type": "tier0",
  "equation_count": 16,
  "source_files": [
    "tier0-computation\\d2_pfaffian_output.txt"
  ],
  "equations": [
    {
      "id": "eq_537",
      "raw": "Xi^2 = I: True",
      "type": "structural",
      "context": "[PART 1] hat{Xi} construction from eq 2.12 G5 diagonal: [-1 -1  1  1 -1 -1 -1 -1  1  1 -1  1  1 -1  1  1]",
      "session": "",
      "source_file": "tier0-computation\\d2_pfaffian_output.txt",
      "line": 7,
      "existing_latex": "",
      "audit_status": "none",
      "new_latex": "",
      "new_status": "",
      "error_note": "",
      "severity": ""
    },
    {
      "id": "eq_538",
      "raw": "CPAIR ev, dim_V=4, alg_rank(real)=8  M_2(C)_embed",
      "type": "structural",
      "context": "Wedderburn: 4 factor(s) (after merging conjugate pairs)",
      "session": "",
      "source_file": "tier0-computation\\d2_pfaffian_output.txt",
      "line": 32,
      "existing_latex": "",
      "audit_status": "none",
      "new_latex": "",
      "new_status": "",
      "error_note": "",
      "severity": ""
    },
    {
      "id": "eq_539",
      "raw": "REAL ev, dim_V=6, alg_rank(real)=36  M_3(H) / M_6(R)",
      "type": "structural",
      "context": "Wedderburn: 4 factor(s) (after merging conjugate pairs) CPAIR ev, dim_V=4, alg_rank(real)=8  M_2(C)_embed",
      "session": "",
      "source_file": "tier0-computation\\d2_pfaffian_output.txt",
      "line": 33,
      "existing_latex": "",
      "audit_status": "none",
      "new_latex": "",
      "new_status": "",
      "error_note": "",
      "severity": ""
    },
    {
      "id": "eq_540",
      "raw": "REAL ev, dim_V=6, alg_rank(real)=4  ?",
      "type": "structural",
      "context": "CPAIR ev, dim_V=4, alg_rank(real)=8  M_2(C)_embed REAL ev, dim_V=6, alg_rank(real)=36  M_3(H) / M_6(R)",
      "session": "",
      "source_file": "tier0-computation\\d2_pfaffian_output.txt",
      "line": 34,
      "existing_latex": "",
      "audit_status": "none",
      "new_latex": "",
      "new_status": "",
      "error_note": "",
      "severity": ""
    },
    {
      "id": "eq_541",
      "raw": "CPAIR ev, dim_V=8, alg_rank(real)=32  M_4(C)_embed",
      "type": "structural",
      "context": "Wedderburn: 3 factor(s) (after merging conjugate pairs)",
      "session": "",
      "source_file": "tier0-computation\\d2_pfaffian_output.txt",
      "line": 52,
      "existing_latex": "",
      "audit_status": "none",
      "new_latex": "",
      "new_status": "",
      "error_note": "",
      "severity": ""
    },
    {
      "id": "eq_542",
      "raw": "CPAIR ev, dim_V=16, alg_rank(real)=32  ?",
      "type": "structural",
      "context": "Wedderburn: 3 factor(s) (after merging conjugate pairs) CPAIR ev, dim_V=8, alg_rank(real)=32  M_4(C)_embed",
      "session": "",
      "source_file": "tier0-computation\\d2_pfaffian_output.txt",
      "line": 53,
      "existing_latex": "",
      "audit_status": "none",
      "new_latex": "",
      "new_status": "",
      "error_note": "",
      "severity": ""
    },
    {
      "id": "eq_543",
      "raw": "REAL ev, dim_V=8, alg_rank(real)=64  M_4(H) / M_8(R)",
      "type": "structural",
      "context": "CPAIR ev, dim_V=8, alg_rank(real)=32  M_4(C)_embed CPAIR ev, dim_V=16, alg_rank(real)=32  ?",
      "session": "",
      "source_file": "tier0-computation\\d2_pfaffian_output.txt",
      "line": 54,
      "existing_latex": "",
      "audit_status": "none",
      "new_latex": "",
      "new_status": "",
      "error_note": "",
      "severity": ""
    },
    {
      "id": "eq_544",
      "raw": "CPAIR ev, dim_V=6, alg_rank(real)=18  M_3(C)_embed",
      "type": "structural",
      "context": "Wedderburn: 4 factor(s) (after merging conjugate pairs) REAL ev, dim_V=2, alg_rank(real)=4  M_1(H) / M_2(R) / H",
      "session": "",
      "source_file": "tier0-computation\\d2_pfaffian_output.txt",
      "line": 72,
      "existing_latex": "",
      "audit_status": "none",
      "new_latex": "",
      "new_status": "",
      "error_note": "",
      "severity": ""
    },
    {
      "id": "eq_545",
      "raw": "CPAIR ev, dim_V=18, alg_rank(real)=18  ?",
      "type": "structural",
      "context": "CPAIR ev, dim_V=6, alg_rank(real)=18  M_3(C)_embed CPAIR ev, dim_V=6, alg_rank(real)=2  ?",
      "session": "",
      "source_file": "tier0-computation\\d2_pfaffian_output.txt",
      "line": 74,
      "existing_latex": "",
      "audit_status": "none",
      "new_latex": "",
      "new_status": "",
      "error_note": "",
      "severity": ""
    },
    {
      "id": "eq_546",
      "raw": "REAL ev, dim_V=2, alg_rank(real)=4  M_1(H) / M_2(R) / H",
      "type": "structural",
      "context": "Wedderburn: 6 factor(s) (after merging conjugate pairs)",
      "session": "",
      "source_file": "tier0-computation\\d2_pfaffian_output.txt",
      "line": 113,
      "existing_latex": "",
      "audit_status": "none",
      "new_latex": "",
      "new_status": "",
      "error_note": "",
      "severity": ""
    },
    {
      "id": "eq_547",
      "raw": "CPAIR ev, dim_V=4, alg_rank(real)=2  ?",
      "type": "structural",
      "context": "Wedderburn: 6 factor(s) (after merging conjugate pairs) REAL ev, dim_V=2, alg_rank(real)=4  M_1(H) / M_2(R) / H",
      "session": "",
      "source_file": "tier0-computation\\d2_pfaffian_output.txt",
      "line": 114,
      "existing_latex": "",
      "audit_status": "none",
      "new_latex": "",
      "new_status": "",
      "error_note": "",
      "severity": ""
    },
    {
      "id": "eq_548",
      "raw": "CPAIR ev, dim_V=6, alg_rank(real)=2  ?",
      "type": "structural",
      "context": "CPAIR ev, dim_V=4, alg_rank(real)=2  ? CPAIR ev, dim_V=6, alg_rank(real)=2  ?",
      "session": "",
      "source_file": "tier0-computation\\d2_pfaffian_output.txt",
      "line": 116,
      "existing_latex": "",
      "audit_status": "none",
      "new_latex": "",
      "new_status": "",
      "error_note": "",
      "severity": ""
    },
    {
      "id": "eq_549",
      "raw": "CPAIR ev, dim_V=12, alg_rank(real)=2  ?",
      "type": "structural",
      "context": "CPAIR ev, dim_V=6, alg_rank(real)=2  ? CPAIR ev, dim_V=6, alg_rank(real)=2  ?",
      "session": "",
      "source_file": "tier0-computation\\d2_pfaffian_output.txt",
      "line": 117,
      "existing_latex": "",
      "audit_status": "none",
      "new_latex": "",
      "new_status": "",
      "error_note": "",
      "severity": ""
    },
    {
      "id": "eq_550",
      "raw": "CPAIR ev, dim_V=2, alg_rank(real)=2  M_1(C)_embed / C",
      "type": "structural",
      "context": "CPAIR ev, dim_V=6, alg_rank(real)=2  ? CPAIR ev, dim_V=12, alg_rank(real)=2  ?",
      "session": "",
      "source_file": "tier0-computation\\d2_pfaffian_output.txt",
      "line": 118,
      "existing_latex": "",
      "audit_status": "none",
      "new_latex": "",
      "new_status": "",
      "error_note": "",
      "severity": ""
    },
    {
      "id": "eq_551",
      "raw": "This is the ONLY gauge giving center dim = 5 (A_F target).",
      "type": "structural",
      "context": "======================================================================",
      "session": "",
      "source_file": "tier0-computation\\d2_pfaffian_output.txt",
      "line": 129,
      "existing_latex": "",
      "audit_status": "none",
      "new_latex": "",
      "new_status": "",
      "error_note": "",
      "severity": ""
    },
    {
      "id": "eq_552",
      "raw": "A_F = C + H + M_3(C)                             24       5        3    PASS",
      "type": "structural",
      "context": "(e) u(2)_{L+R} + R_{su(3)} [combined + right]    14      11        6    FAIL",
      "session": "",
      "source_file": "tier0-computation\\d2_pfaffian_output.txt",
      "line": 189,
      "existing_latex": "",
      "audit_status": "none",
      "new_latex": "",
      "new_status": "",
      "error_note": "",
      "severity": ""
    }
  ]
}