{
  "batch_id": "tier0-computation_batch_0269",
  "source_type": "tier0",
  "equation_count": 50,
  "source_files": [
    "tier0-computation\\test_AF_rowaction.py"
  ],
  "equations": [
    {
      "id": "eq_10807",
      "raw": "gamma_F = np.zeros((32, 32))",
      "type": "code",
      "context": "Xi[16:, :16] = -G5",
      "session": "",
      "source_file": "tier0-computation\\test_AF_rowaction.py",
      "line": 66,
      "existing_latex": "",
      "audit_status": "none",
      "new_latex": "",
      "new_status": "",
      "error_note": "",
      "severity": ""
    },
    {
      "id": "eq_10808",
      "raw": "R_u2_gens_16 = [R_action_matrix(v) for v in basis_u2]",
      "type": "code",
      "context": "R_{u(2)} generators on C^32",
      "session": "",
      "source_file": "tier0-computation\\test_AF_rowaction.py",
      "line": 85,
      "existing_latex": "",
      "audit_status": "none",
      "new_latex": "",
      "new_status": "",
      "error_note": "",
      "severity": ""
    },
    {
      "id": "eq_10809",
      "raw": "if row == 0: return col          # (0,1)=1, (0,2)=2, (0,3)=3",
      "type": "code",
      "context": "\"\"\"Convert 4x4 matrix index (row, col) to Baptista flat 16-index.\"\"\" if row == 0 and col == 0: return 0",
      "session": "",
      "source_file": "tier0-computation\\test_AF_rowaction.py",
      "line": 98,
      "existing_latex": "",
      "audit_status": "none",
      "new_latex": "",
      "new_status": "",
      "error_note": "",
      "severity": ""
    },
    {
      "id": "eq_10810",
      "raw": "if col == 0: return row + 3      # (1,0)=4, (2,0)=5, (3,0)=6",
      "type": "code",
      "context": "if row == 0 and col == 0: return 0 if row == 0: return col          (0,1)=1, (0,2)=2, (0,3)=3",
      "session": "",
      "source_file": "tier0-computation\\test_AF_rowaction.py",
      "line": 99,
      "existing_latex": "",
      "audit_status": "none",
      "new_latex": "",
      "new_status": "",
      "error_note": "",
      "severity": ""
    },
    {
      "id": "eq_10811",
      "raw": "L_m = np.zeros((4, 4), dtype=complex)",
      "type": "code",
      "context": "for a in range(3): for b in range(3):",
      "session": "",
      "source_file": "tier0-computation\\test_AF_rowaction.py",
      "line": 164,
      "existing_latex": "",
      "audit_status": "none",
      "new_latex": "",
      "new_status": "",
      "error_note": "",
      "severity": ""
    },
    {
      "id": "eq_10812",
      "raw": "L_m[0, 0] = 0.0  # NOT identity on row 0; just the E_{ab} piece",
      "type": "code",
      "context": "for b in range(3): L_m = np.zeros((4, 4), dtype=complex)",
      "session": "",
      "source_file": "tier0-computation\\test_AF_rowaction.py",
      "line": 165,
      "existing_latex": "",
      "audit_status": "none",
      "new_latex": "",
      "new_status": "",
      "error_note": "",
      "severity": ""
    },
    {
      "id": "eq_10813",
      "raw": "gen_16 = build_left_action_16(L_m)",
      "type": "code",
      "context": "L_m[0, 0] = 0.0  NOT identity on row 0; just the E_{ab} piece L_m[a + 1, b + 1] = 1.0",
      "session": "",
      "source_file": "tier0-computation\\test_AF_rowaction.py",
      "line": 167,
      "existing_latex": "",
      "audit_status": "none",
      "new_latex": "",
      "new_status": "",
      "error_note": "",
      "severity": ""
    },
    {
      "id": "eq_10814",
      "raw": "color_gens_32 = [build_full_32(g) for g in color_gens_16]",
      "type": "code",
      "context": "Extend to C^32",
      "session": "",
      "source_file": "tier0-computation\\test_AF_rowaction.py",
      "line": 172,
      "existing_latex": "",
      "audit_status": "none",
      "new_latex": "",
      "new_status": "",
      "error_note": "",
      "severity": ""
    },
    {
      "id": "eq_10815",
      "raw": "comm = E32 @ Rv - Rv @ E32",
      "type": "code",
      "context": "for ci, (E32, cn) in enumerate(zip(color_gens_32, color_names)): for gi, Rv in enumerate(R_u2_gens_32):",
      "session": "",
      "source_file": "tier0-computation\\test_AF_rowaction.py",
      "line": 182,
      "existing_latex": "",
      "audit_status": "none",
      "new_latex": "",
      "new_status": "",
      "error_note": "",
      "severity": ""
    },
    {
      "id": "eq_10816",
      "raw": "gate_max = max(gate_max, err)",
      "type": "code",
      "context": "comm = E32 @ Rv - Rv @ E32 err = np.max(np.abs(comm))",
      "session": "",
      "source_file": "tier0-computation\\test_AF_rowaction.py",
      "line": 184,
      "existing_latex": "",
      "audit_status": "none",
      "new_latex": "",
      "new_status": "",
      "error_note": "",
      "severity": ""
    },
    {
      "id": "eq_10817",
      "raw": "AF_factor = []  # Track which factor each generator belongs to",
      "type": "code",
      "context": "AF_gens_16 = [] AF_names = []",
      "session": "",
      "source_file": "tier0-computation\\test_AF_rowaction.py",
      "line": 206,
      "existing_latex": "",
      "audit_status": "none",
      "new_latex": "",
      "new_status": "",
      "error_note": "",
      "severity": ""
    },
    {
      "id": "eq_10818",
      "raw": "L_C_Re = np.zeros((4, 4), dtype=complex)",
      "type": "code",
      "context": "C generator 1: Re(lambda) -- projection onto row 0",
      "session": "",
      "source_file": "tier0-computation\\test_AF_rowaction.py",
      "line": 225,
      "existing_latex": "",
      "audit_status": "none",
      "new_latex": "",
      "new_status": "",
      "error_note": "",
      "severity": ""
    },
    {
      "id": "eq_10819",
      "raw": "L_C_Im = np.zeros((4, 4), dtype=complex)",
      "type": "code",
      "context": "C generator 2: Im(lambda) -- i * projection onto row 0",
      "session": "",
      "source_file": "tier0-computation\\test_AF_rowaction.py",
      "line": 232,
      "existing_latex": "",
      "audit_status": "none",
      "new_latex": "",
      "new_status": "",
      "error_note": "",
      "severity": ""
    },
    {
      "id": "eq_10820",
      "raw": "L_H_1 = np.eye(4, dtype=complex)",
      "type": "code",
      "context": "H_1: q=1 -> alpha=1, bar_alpha=1, q_2x2=I_2 L = diag(1, 1, 1, 1) = I_4  (identity)",
      "session": "",
      "source_file": "tier0-computation\\test_AF_rowaction.py",
      "line": 499,
      "existing_latex": "",
      "audit_status": "none",
      "new_latex": "",
      "new_status": "",
      "error_note": "",
      "severity": ""
    },
    {
      "id": "eq_10821",
      "raw": "L_H_i = np.diag([1j, -1j, 1j, -1j])",
      "type": "code",
      "context": "H_i: q=i -> alpha=i, bar_alpha=-i, q_2x2=diag(i,-i) L = diag(i, -i, i, -i)",
      "session": "",
      "source_file": "tier0-computation\\test_AF_rowaction.py",
      "line": 506,
      "existing_latex": "",
      "audit_status": "none",
      "new_latex": "",
      "new_status": "",
      "error_note": "",
      "severity": ""
    },
    {
      "id": "eq_10822",
      "raw": "L_H_j = np.zeros((4, 4), dtype=complex)",
      "type": "code",
      "context": "H_j: q=j -> alpha=0, bar_alpha=0, q_2x2=[[0,1],[-1,0]] L = diag(0, 0, [[0,1],[-1,0]])",
      "session": "",
      "source_file": "tier0-computation\\test_AF_rowaction.py",
      "line": 513,
      "existing_latex": "",
      "audit_status": "none",
      "new_latex": "",
      "new_status": "",
      "error_note": "",
      "severity": ""
    },
    {
      "id": "eq_10823",
      "raw": "L_H_j[3, 2] = -1.0",
      "type": "code",
      "context": "L_H_j = np.zeros((4, 4), dtype=complex) L_H_j[2, 3] = 1.0",
      "session": "",
      "source_file": "tier0-computation\\test_AF_rowaction.py",
      "line": 515,
      "existing_latex": "",
      "audit_status": "none",
      "new_latex": "",
      "new_status": "",
      "error_note": "",
      "severity": ""
    },
    {
      "id": "eq_10824",
      "raw": "L_H_k = np.zeros((4, 4), dtype=complex)",
      "type": "code",
      "context": "H_k: q=k -> alpha=0, bar_alpha=0, q_2x2=[[0,i],[i,0]] L = diag(0, 0, [[0,i],[i,0]])",
      "session": "",
      "source_file": "tier0-computation\\test_AF_rowaction.py",
      "line": 522,
      "existing_latex": "",
      "audit_status": "none",
      "new_latex": "",
      "new_status": "",
      "error_note": "",
      "severity": ""
    },
    {
      "id": "eq_10825",
      "raw": "test_id = build_left_action_16(np.eye(4, dtype=complex))",
      "type": "code",
      "context": "print(\"\\n\" + \"-\" * 76) print(\"[TEST 1] Verify build_left_action_16 gives correct identity\")",
      "session": "",
      "source_file": "tier0-computation\\test_AF_rowaction.py",
      "line": 557,
      "existing_latex": "",
      "audit_status": "none",
      "new_latex": "",
      "new_status": "",
      "error_note": "",
      "severity": ""
    },
    {
      "id": "eq_10826",
      "raw": "err_id = np.max(np.abs(test_id - np.eye(16)))",
      "type": "code",
      "context": "print(\"[TEST 1] Verify build_left_action_16 gives correct identity\") test_id = build_left_action_16(np.eye(4, dtype=complex))",
      "session": "",
      "source_file": "tier0-computation\\test_AF_rowaction.py",
      "line": 558,
      "existing_latex": "",
      "audit_status": "none",
      "new_latex": "",
      "new_status": "",
      "error_note": "",
      "severity": ""
    },
    {
      "id": "eq_10827",
      "raw": "fi = flat_idx(r, c)",
      "type": "code",
      "context": "row_str = \"  row \" + str(r) + \": \" for c in range(4):",
      "session": "",
      "source_file": "tier0-computation\\test_AF_rowaction.py",
      "line": 566,
      "existing_latex": "",
      "audit_status": "none",
      "new_latex": "",
      "new_status": "",
      "error_note": "",
      "severity": ""
    },
    {
      "id": "eq_10828",
      "raw": "Hi = AF_gens_32[AF_names.index('H_i')]",
      "type": "code",
      "context": "print(\"\\n\" + \"-\" * 76) print(\"[TEST 5] Quaternion relations in H factor\")",
      "session": "",
      "source_file": "tier0-computation\\test_AF_rowaction.py",
      "line": 623,
      "existing_latex": "",
      "audit_status": "none",
      "new_latex": "",
      "new_status": "",
      "error_note": "",
      "severity": ""
    },
    {
      "id": "eq_10829",
      "raw": "Hj = AF_gens_32[AF_names.index('H_j')]",
      "type": "code",
      "context": "print(\"[TEST 5] Quaternion relations in H factor\") Hi = AF_gens_32[AF_names.index('H_i')]",
      "session": "",
      "source_file": "tier0-computation\\test_AF_rowaction.py",
      "line": 624,
      "existing_latex": "",
      "audit_status": "none",
      "new_latex": "",
      "new_status": "",
      "error_note": "",
      "severity": ""
    },
    {
      "id": "eq_10830",
      "raw": "Hk = AF_gens_32[AF_names.index('H_k')]",
      "type": "code",
      "context": "Hi = AF_gens_32[AF_names.index('H_i')] Hj = AF_gens_32[AF_names.index('H_j')]",
      "session": "",
      "source_file": "tier0-computation\\test_AF_rowaction.py",
      "line": 625,
      "existing_latex": "",
      "audit_status": "none",
      "new_latex": "",
      "new_status": "",
      "error_note": "",
      "severity": ""
    },
    {
      "id": "eq_10831",
      "raw": "H1 = AF_gens_32[AF_names.index('H_1')]",
      "type": "code",
      "context": "Hj = AF_gens_32[AF_names.index('H_j')] Hk = AF_gens_32[AF_names.index('H_k')]",
      "session": "",
      "source_file": "tier0-computation\\test_AF_rowaction.py",
      "line": 626,
      "existing_latex": "",
      "audit_status": "none",
      "new_latex": "",
      "new_status": "",
      "error_note": "",
      "severity": ""
    },
    {
      "id": "eq_10832",
      "raw": "('j^2=-1', Hj @ Hj, -H1),",
      "type": "code",
      "context": "for label, prod, exp in [ ('i^2=-1', Hi @ Hi, -H1),",
      "session": "",
      "source_file": "tier0-computation\\test_AF_rowaction.py",
      "line": 630,
      "existing_latex": "",
      "audit_status": "none",
      "new_latex": "",
      "new_status": "",
      "error_note": "",
      "severity": ""
    },
    {
      "id": "eq_10833",
      "raw": "('k^2=-1', Hk @ Hk, -H1),",
      "type": "code",
      "context": "('i^2=-1', Hi @ Hi, -H1), ('j^2=-1', Hj @ Hj, -H1),",
      "session": "",
      "source_file": "tier0-computation\\test_AF_rowaction.py",
      "line": 631,
      "existing_latex": "",
      "audit_status": "none",
      "new_latex": "",
      "new_status": "",
      "error_note": "",
      "severity": ""
    },
    {
      "id": "eq_10834",
      "raw": "('ij=k', Hi @ Hj, Hk),",
      "type": "code",
      "context": "('j^2=-1', Hj @ Hj, -H1), ('k^2=-1', Hk @ Hk, -H1),",
      "session": "",
      "source_file": "tier0-computation\\test_AF_rowaction.py",
      "line": 632,
      "existing_latex": "",
      "audit_status": "none",
      "new_latex": "",
      "new_status": "",
      "error_note": "",
      "severity": ""
    },
    {
      "id": "eq_10835",
      "raw": "('jk=i', Hj @ Hk, Hi),",
      "type": "code",
      "context": "('k^2=-1', Hk @ Hk, -H1), ('ij=k', Hi @ Hj, Hk),",
      "session": "",
      "source_file": "tier0-computation\\test_AF_rowaction.py",
      "line": 633,
      "existing_latex": "",
      "audit_status": "none",
      "new_latex": "",
      "new_status": "",
      "error_note": "",
      "severity": ""
    },
    {
      "id": "eq_10836",
      "raw": "('ki=j', Hk @ Hi, Hj),",
      "type": "code",
      "context": "('ij=k', Hi @ Hj, Hk), ('jk=i', Hj @ Hk, Hi),",
      "session": "",
      "source_file": "tier0-computation\\test_AF_rowaction.py",
      "line": 634,
      "existing_latex": "",
      "audit_status": "none",
      "new_latex": "",
      "new_status": "",
      "error_note": "",
      "severity": ""
    },
    {
      "id": "eq_10837",
      "raw": "err = np.max(np.abs(prod - exp))",
      "type": "code",
      "context": "('ki=j', Hk @ Hi, Hj), ]:",
      "session": "",
      "source_file": "tier0-computation\\test_AF_rowaction.py",
      "line": 636,
      "existing_latex": "",
      "audit_status": "none",
      "new_latex": "",
      "new_status": "",
      "error_note": "",
      "severity": ""
    },
    {
      "id": "eq_10838",
      "raw": "worst_pair = ('', '', 0)",
      "type": "code",
      "context": "max_oz = 0 n_viol = 0",
      "session": "",
      "source_file": "tier0-computation\\test_AF_rowaction.py",
      "line": 645,
      "existing_latex": "",
      "audit_status": "none",
      "new_latex": "",
      "new_status": "",
      "error_note": "",
      "severity": ""
    },
    {
      "id": "eq_10839",
      "raw": "v = np.concatenate([T.flatten().real, T.flatten().imag])",
      "type": "code",
      "context": "indep_vecs = [] for i, T in enumerate(AF_gens_32):",
      "session": "",
      "source_file": "tier0-computation\\test_AF_rowaction.py",
      "line": 683,
      "existing_latex": "",
      "audit_status": "none",
      "new_latex": "",
      "new_status": "",
      "error_note": "",
      "severity": ""
    },
    {
      "id": "eq_10840",
      "raw": "M = np.column_stack(indep_vecs)",
      "type": "code",
      "context": "indep_vecs.append(v) else:",
      "session": "",
      "source_file": "tier0-computation\\test_AF_rowaction.py",
      "line": 688,
      "existing_latex": "",
      "audit_status": "none",
      "new_latex": "",
      "new_status": "",
      "error_note": "",
      "severity": ""
    },
    {
      "id": "eq_10841",
      "raw": "coeffs = np.linalg.lstsq(M, v, rcond=None)[0]",
      "type": "code",
      "context": "else: M = np.column_stack(indep_vecs)",
      "session": "",
      "source_file": "tier0-computation\\test_AF_rowaction.py",
      "line": 689,
      "existing_latex": "",
      "audit_status": "none",
      "new_latex": "",
      "new_status": "",
      "error_note": "",
      "severity": ""
    },
    {
      "id": "eq_10842",
      "raw": "resid = np.linalg.norm(v - M @ coeffs)",
      "type": "code",
      "context": "M = np.column_stack(indep_vecs) coeffs = np.linalg.lstsq(M, v, rcond=None)[0]",
      "session": "",
      "source_file": "tier0-computation\\test_AF_rowaction.py",
      "line": 690,
      "existing_latex": "",
      "audit_status": "none",
      "new_latex": "",
      "new_status": "",
      "error_note": "",
      "severity": ""
    },
    {
      "id": "eq_10843",
      "raw": "gen_mats = [AF_gens_32[i] for i in indep_idx]",
      "type": "code",
      "context": "Check closure: all products in the span?",
      "session": "",
      "source_file": "tier0-computation\\test_AF_rowaction.py",
      "line": 698,
      "existing_latex": "",
      "audit_status": "none",
      "new_latex": "",
      "new_status": "",
      "error_note": "",
      "severity": ""
    },
    {
      "id": "eq_10844",
      "raw": "Q_gens = orth(np.column_stack(indep_vecs))",
      "type": "code",
      "context": "Check closure: all products in the span? gen_mats = [AF_gens_32[i] for i in indep_idx]",
      "session": "",
      "source_file": "tier0-computation\\test_AF_rowaction.py",
      "line": 699,
      "existing_latex": "",
      "audit_status": "none",
      "new_latex": "",
      "new_status": "",
      "error_note": "",
      "severity": ""
    },
    {
      "id": "eq_10845",
      "raw": "d_gens = Q_gens.shape[1]",
      "type": "code",
      "context": "gen_mats = [AF_gens_32[i] for i in indep_idx] Q_gens = orth(np.column_stack(indep_vecs))",
      "session": "",
      "source_file": "tier0-computation\\test_AF_rowaction.py",
      "line": 700,
      "existing_latex": "",
      "audit_status": "none",
      "new_latex": "",
      "new_status": "",
      "error_note": "",
      "severity": ""
    },
    {
      "id": "eq_10846",
      "raw": "prod = T1 @ T2",
      "type": "code",
      "context": "for T1 in gen_mats: for T2 in gen_mats:",
      "session": "",
      "source_file": "tier0-computation\\test_AF_rowaction.py",
      "line": 705,
      "existing_latex": "",
      "audit_status": "none",
      "new_latex": "",
      "new_status": "",
      "error_note": "",
      "severity": ""
    },
    {
      "id": "eq_10847",
      "raw": "pv = np.concatenate([prod.flatten().real, prod.flatten().imag])",
      "type": "code",
      "context": "for T2 in gen_mats: prod = T1 @ T2",
      "session": "",
      "source_file": "tier0-computation\\test_AF_rowaction.py",
      "line": 706,
      "existing_latex": "",
      "audit_status": "none",
      "new_latex": "",
      "new_status": "",
      "error_note": "",
      "severity": ""
    },
    {
      "id": "eq_10848",
      "raw": "coeffs = Q_gens.T @ pv",
      "type": "code",
      "context": "prod = T1 @ T2 pv = np.concatenate([prod.flatten().real, prod.flatten().imag])",
      "session": "",
      "source_file": "tier0-computation\\test_AF_rowaction.py",
      "line": 707,
      "existing_latex": "",
      "audit_status": "none",
      "new_latex": "",
      "new_status": "",
      "error_note": "",
      "severity": ""
    },
    {
      "id": "eq_10849",
      "raw": "resid = np.linalg.norm(pv - Q_gens @ coeffs)",
      "type": "code",
      "context": "pv = np.concatenate([prod.flatten().real, prod.flatten().imag]) coeffs = Q_gens.T @ pv",
      "session": "",
      "source_file": "tier0-computation\\test_AF_rowaction.py",
      "line": 708,
      "existing_latex": "",
      "audit_status": "none",
      "new_latex": "",
      "new_status": "",
      "error_note": "",
      "severity": ""
    },
    {
      "id": "eq_10850",
      "raw": "max_resid = max(max_resid, resid)",
      "type": "code",
      "context": "coeffs = Q_gens.T @ pv resid = np.linalg.norm(pv - Q_gens @ coeffs)",
      "session": "",
      "source_file": "tier0-computation\\test_AF_rowaction.py",
      "line": 709,
      "existing_latex": "",
      "audit_status": "none",
      "new_latex": "",
      "new_status": "",
      "error_note": "",
      "severity": ""
    },
    {
      "id": "eq_10851",
      "raw": "Q_cur = Q_gens.copy()",
      "type": "code",
      "context": "print(\"  Computing algebraic closure...\") n_flat = 32 * 32",
      "session": "",
      "source_file": "tier0-computation\\test_AF_rowaction.py",
      "line": 718,
      "existing_latex": "",
      "audit_status": "none",
      "new_latex": "",
      "new_status": "",
      "error_note": "",
      "severity": ""
    },
    {
      "id": "eq_10852",
      "raw": "cur_basis = [(Q_cur[:, k][:n_flat] + 1j * Q_cur[:, k][n_flat:]).reshape(32, 32)",
      "type": "code",
      "context": "for iteration in range(10):",
      "session": "",
      "source_file": "tier0-computation\\test_AF_rowaction.py",
      "line": 722,
      "existing_latex": "",
      "audit_status": "none",
      "new_latex": "",
      "new_status": "",
      "error_note": "",
      "severity": ""
    },
    {
      "id": "eq_10853",
      "raw": "all_v = np.column_stack([Q_cur] + [np.column_stack(new_vecs)])",
      "type": "code",
      "context": "if not new_vecs: break",
      "session": "",
      "source_file": "tier0-computation\\test_AF_rowaction.py",
      "line": 735,
      "existing_latex": "",
      "audit_status": "none",
      "new_latex": "",
      "new_status": "",
      "error_note": "",
      "severity": ""
    },
    {
      "id": "eq_10854",
      "raw": "Q_new = orth(all_v)",
      "type": "code",
      "context": "break all_v = np.column_stack([Q_cur] + [np.column_stack(new_vecs)])",
      "session": "",
      "source_file": "tier0-computation\\test_AF_rowaction.py",
      "line": 736,
      "existing_latex": "",
      "audit_status": "none",
      "new_latex": "",
      "new_status": "",
      "error_note": "",
      "severity": ""
    },
    {
      "id": "eq_10855",
      "raw": "d_new = Q_new.shape[1]",
      "type": "code",
      "context": "all_v = np.column_stack([Q_cur] + [np.column_stack(new_vecs)]) Q_new = orth(all_v)",
      "session": "",
      "source_file": "tier0-computation\\test_AF_rowaction.py",
      "line": 737,
      "existing_latex": "",
      "audit_status": "none",
      "new_latex": "",
      "new_status": "",
      "error_note": "",
      "severity": ""
    },
    {
      "id": "eq_10856",
      "raw": "(0,0)=0:nu_R   (0,1)=1:u_R^r  (0,2)=2:u_R^g  (0,3)=3:u_R^b     row 0",
      "type": "comment",
      "context": "── Flat index mapping (Baptista convention) ── Psi_+ as 4x4 matrix:",
      "session": "",
      "source_file": "tier0-computation\\test_AF_rowaction.py",
      "line": 90,
      "existing_latex": "",
      "audit_status": "none",
      "new_latex": "",
      "new_status": "",
      "error_note": "",
      "severity": ""
    }
  ]
}