{
  "batch_id": "tier0-computation_batch_0288",
  "source_type": "tier0",
  "equation_count": 1,
  "source_files": [
    "tier0-computation\\tier1_dirac_spectrum.py"
  ],
  "equations": [
    {
      "id": "eq_11596",
      "raw": "--- Step 5: Single deformed spectrum (s=0.5 test) ---",
      "type": "comment",
      "context": "phi_pairs_0, gold_pairs_0 = analyze_nonconsecutive_ratios(abs_evals_0, verbose=True)",
      "session": "",
      "source_file": "tier0-computation\\tier1_dirac_spectrum.py",
      "line": 1798,
      "existing_latex": "",
      "audit_status": "none",
      "new_latex": "",
      "new_status": "",
      "error_note": "",
      "severity": ""
    }
  ]
}