{
  "batch_id": "tier0-computation_batch_0132",
  "source_type": "tier0",
  "equation_count": 3,
  "source_files": [
    "tier0-computation\\s19a_level_statistics.py"
  ],
  "equations": [
    {
      "id": "eq_5937",
      "raw": "tc_best = results['tau_c_global'] or results['tau_c_intra']",
      "type": "code",
      "context": "print(\"  >>   of what information the current eigenvalue data contains.\") elif q_max_global > 0.2 or q_max_intra > 0.2:",
      "session": "19a",
      "source_file": "tier0-computation\\s19a_level_statistics.py",
      "line": 752,
      "existing_latex": "",
      "audit_status": "none",
      "new_latex": "",
      "new_status": "",
      "error_note": "",
      "severity": ""
    },
    {
      "id": "eq_5938",
      "raw": "Panel (c): P(s) histograms at tau=0, mid, end — GLOBAL DISTINCT",
      "type": "comment",
      "context": "ax.grid(True, alpha=0.3)",
      "session": "19a",
      "source_file": "tier0-computation\\s19a_level_statistics.py",
      "line": 572,
      "existing_latex": "",
      "audit_status": "none",
      "new_latex": "",
      "new_status": "",
      "error_note": "",
      "severity": ""
    },
    {
      "id": "eq_5939",
      "raw": "====== PLOT 2: Intra-sector P(s) detail ======",
      "type": "comment",
      "context": "print(f\"  Saved: {path}\")",
      "session": "19a",
      "source_file": "tier0-computation\\s19a_level_statistics.py",
      "line": 625,
      "existing_latex": "",
      "audit_status": "none",
      "new_latex": "",
      "new_status": "",
      "error_note": "",
      "severity": ""
    }
  ]
}